vrouter_agent/__init__.py
vrouter_agent/agent.py
vrouter_agent/alembic/README
vrouter_agent/alembic/env.py
vrouter_agent/alembic/script.py.mako
vrouter_agent/alembic/versions/1180d19201bd_add_topology_id_to_tunnel_config.py
vrouter_agent/alembic/versions/21c9f27314b4_add_client_interfaces_column_to_tunnel_.py
vrouter_agent/alembic/versions/630b2588379d_merge_topology_id_and_remove_vpp_.py
vrouter_agent/alembic/versions/a16afcd7955d_fix_tunnel_config_schema_remove_legacy_.py
vrouter_agent/alembic/versions/acb2cb4a8198_add_vpp_interface_mappings_to_tunnel_.py
vrouter_agent/alembic/versions/b4d7e8f5c1a2_add_bgp_peers_column_to_tunnel_config.py
vrouter_agent/alembic/versions/c8f9d2e5a1b3_add_protocol_enablement_flags_to_tunnel_config.py
vrouter_agent/alembic/versions/d9e8f3a6b2c4_add_nat_acl_config_columns_to_tunnel_config.py
vrouter_agent/alembic/versions/remove_vpp_mappings_field.py
vrouter_agent/alembic.ini
vrouter_agent/api/README.md
vrouter_agent/api/__init__.py
vrouter_agent/api/orders.py
vrouter_agent/api/root.py
vrouter_agent/api/telemetry.py
vrouter_agent/api/transactions.py
vrouter_agent/api/tunnel_config.py
vrouter_agent/config_manager.py
vrouter_agent/core/__init__.py
vrouter_agent/core/base.py
vrouter_agent/core/config.py
vrouter_agent/core/db.py
vrouter_agent/core/enums.py
vrouter_agent/core/frr_config.py
vrouter_agent/core/models.py
vrouter_agent/demo/generate_client_frr_config.py
vrouter_agent/demo/generators/main.py
vrouter_agent/demo/rr.py
vrouter_agent/demo/vpp1.py
vrouter_agent/demo/vpp1_api.py
vrouter_agent/demo/vpp1_cli.py
vrouter_agent/demo/vpp1_failover_notifier.py
vrouter_agent/demo/vpp2.py
vrouter_agent/demo/vpp2_api.py
vrouter_agent/demo/vpp2_cli.py
vrouter_agent/demo/vpp2_failover_notifier.py
vrouter_agent/demo/vpp3_api.py
vrouter_agent/demo/vpp3_cli.py
vrouter_agent/demo/vpp4_api.py
vrouter_agent/demo/vpp4_cli.py
vrouter_agent/enhanced_stream_processor.py
vrouter_agent/examples/__init__.py
vrouter_agent/examples/enhanced_client_example.py
vrouter_agent-1.6.2.dist-info/LICENSE
vrouter_agent-1.6.2.dist-info/METADATA
vrouter_agent-1.6.2.dist-info/WHEEL
vrouter_agent-1.6.2.dist-info/entry_points.txt
vrouter_agent-1.6.2.dist-info/RECORD
