Metadata-Version: 2.1
Name: vrouter-agent
Version: 1.6.2
Summary: USDN vRouter-agent to execute order on each node
Home-page: https://github.com/Unified-Sentinel-Data-Networks/vrouter-agent
License: US Data Networks. All rights reserved.
Keywords: vrouter,networking,agent,multichain,wireguard
Author: Phan Dang
Author-email: phan.dang@usdatanetworks.com
Requires-Python: >=3.10,<4.0
Classifier: Development Status :: 4 - Beta
Classifier: Intended Audience :: Developers
Classifier: Intended Audience :: System Administrators
Classifier: License :: Other/Proprietary License
Classifier: Operating System :: POSIX :: Linux
Classifier: Programming Language :: Python :: 3
Classifier: Programming Language :: Python :: 3.10
Classifier: Programming Language :: Python :: 3.11
Classifier: Topic :: Software Development :: Libraries :: Python Modules
Classifier: Topic :: System :: Networking
Provides-Extra: all
Provides-Extra: monitoring
Provides-Extra: performance
Provides-Extra: testing
Requires-Dist: alembic (>=1.12.1,<2.0.0)
Requires-Dist: asyncio-throttle (>=1.0.2,<2.0.0)
Requires-Dist: cffi
Requires-Dist: cryptography (>=41.0.0,<42.0.0)
Requires-Dist: dataclasses-json (>=0.5.7,<0.6.0)
Requires-Dist: faker (>=35.0.0,<36.0.0) ; extra == "testing" or extra == "all"
Requires-Dist: fastapi (>=0.116.1,<0.117.0)
Requires-Dist: httpx (>=0.28.0,<0.29.0) ; extra == "testing" or extra == "all"
Requires-Dist: loguru (>=0.7.0,<0.8.0)
Requires-Dist: mcrpc (>=2.0.6.0,<3.0.0.0)
Requires-Dist: memory-profiler (>=0.61.0,<0.62.0) ; extra == "performance" or extra == "all"
Requires-Dist: prometheus-client (>=0.20.0,<0.21.0) ; extra == "monitoring" or extra == "all"
Requires-Dist: psutil (>=5.9.8,<6.0.0)
Requires-Dist: py-spy (>=0.4.0,<0.5.0) ; extra == "performance" or extra == "all"
Requires-Dist: pydantic (>=2.9.0,<3.0.0)
Requires-Dist: pydantic-settings (>=2.10.1,<3.0.0)
Requires-Dist: pytest-asyncio (>=0.24.0,<0.25.0) ; extra == "testing" or extra == "all"
Requires-Dist: pytest-cov (>=6.0.0,<7.0.0) ; extra == "testing" or extra == "all"
Requires-Dist: pytest-mock (>=3.14.0,<4.0.0) ; extra == "testing" or extra == "all"
Requires-Dist: python-multipart (>=0.0.12,<0.0.13)
Requires-Dist: pyyaml (>=6.0.1,<7.0.0)
Requires-Dist: simplejson (>=3.19.1,<4.0.0)
Requires-Dist: sqlmodel (>=0.0.24,<0.0.25)
Requires-Dist: structlog (>=23.0.0,<24.0.0) ; extra == "monitoring" or extra == "all"
Requires-Dist: tenacity (>=8.2.3,<9.0.0)
Requires-Dist: typing-extensions (>=4.15.0,<5.0.0)
Requires-Dist: uvicorn (>=0.30.6,<0.31.0)
Requires-Dist: vpp-vrouter (>=0.1.28,<0.2.0)
Requires-Dist: wgconfig (>=1.1.0,<2.0.0)
Project-URL: Documentation, https://github.com/Unified-Sentinel-Data-Networks/vrouter-agent/blob/main/README.md
Project-URL: Repository, https://github.com/Unified-Sentinel-Data-Networks/vrouter-agent
